main.py
mseep_mcpdemo-0.1.2.dist-info/METADATA
mseep_mcpdemo-0.1.2.dist-info/WHEEL
mseep_mcpdemo-0.1.2.dist-info/entry_points.txt
mseep_mcpdemo-0.1.2.dist-info/top_level.txt
mseep_mcpdemo-0.1.2.dist-info/RECORD
